compal/__init__.py
compal/functions.py
compal/models.py
compal-0.3.2.dist-info/LICENSE.txt
compal-0.3.2.dist-info/METADATA
compal-0.3.2.dist-info/WHEEL
compal-0.3.2.dist-info/top_level.txt
compal-0.3.2.dist-info/RECORD
