Metadata-Version: 2.1
Name: compal
Version: 0.3.2
Summary: Compal CH7465LG/Ziggo Connect Box client
Home-page: https://github.com/ties/compal_CH7465LG_py
Author: Ties de Kock
Author-email: ties@tiesdekock.nl
License: MIT
Keywords: compal CH7465LG connect box cablemodem
Platform: UNKNOWN
Classifier: Development Status :: 5 - Production/Stable
Classifier: Topic :: Software Development :: Libraries
Classifier: License :: OSI Approved :: MIT License
Requires-Python: >=3.7
Requires-Dist: requests
Requires-Dist: lxml
